sacn/__init__.py
sacn/receiver.py
sacn/receiver_test.py
sacn/sender.py
sacn/sender_test.py
sacn/messages/__init__.py
sacn/messages/data_packet.py
sacn/messages/data_packet_test.py
sacn/messages/data_types.py
sacn/messages/data_types_test.py
sacn/messages/general_test.py
sacn/messages/root_layer.py
sacn/messages/root_layer_test.py
sacn/messages/sync_packet.py
sacn/messages/sync_packet_test.py
sacn/messages/universe_discovery.py
sacn/messages/universe_discovery_test.py
sacn/receiving/__init__.py
sacn/receiving/receiver_handler.py
sacn/receiving/receiver_handler_test.py
sacn/receiving/receiver_socket_base.py
sacn/receiving/receiver_socket_base_test.py
sacn/receiving/receiver_socket_test.py
sacn/receiving/receiver_socket_udp.py
sacn/sending/__init__.py
sacn/sending/output.py
sacn/sending/sender_handler.py
sacn/sending/sender_handler_test.py
sacn/sending/sender_socket_base.py
sacn/sending/sender_socket_base_test.py
sacn/sending/sender_socket_test.py
sacn/sending/sender_socket_udp.py
sacn-1.10.0.dist-info/LICENSE
sacn-1.10.0.dist-info/METADATA
sacn-1.10.0.dist-info/WHEEL
sacn-1.10.0.dist-info/top_level.txt
sacn-1.10.0.dist-info/RECORD
