Metadata-Version: 2.1
Name: sacn
Version: 1.10.0
Summary: sACN / E1.31 module for easy handling of DMX data over ethernet
Home-page: https://www.github.com/Hundemeier/sacn
Author: Hundemeier
Author-email: hundemeier99@gmail.com
License: MIT License
Keywords: sacn e131 e1.31 dmx
Classifier: Programming Language :: Python :: 3 :: Only
Classifier: License :: OSI Approved :: MIT License
Classifier: Operating System :: OS Independent
Requires-Python: >=3.6
License-File: LICENSE
